{
  "cli": {
    "version": ">= 5.0.0",
    "appVersionSource": "local"
  },
  "build": {
    "local": {
      "distribution": "internal",
      "developmentClient": true,
      "android": {
        "buildType": "apk"
      },
      "ios": {
        "simulator": true
      }
    },
    "development": {
      "developmentClient": true,
      "distribution": "internal"
    },
    "preview": {
      "distribution": "internal",
      "autoIncrement": false,
      "ios": {
        "buildConfiguration": "Release"
      }
    },
    "production": {
      "distribution": "store",
      "autoIncrement": true,
      "ios": {
        "buildConfiguration": "Release"
      },
      "submit": true
    }
  },
  "submit": {
    "preview": {
      "android": {
        "track": "internal"
      },
      "ios": {}
    },
    "production": {
      "android": {
        "track": "production"
      },
      "ios": {}
    }
  }
}